Metadata-Version: 2.1
Name: python-libfprint
Version: 0.0.1
Summary: A fprint library wrapper
Home-page: UNKNOWN
Author: Diego Saraiva
Author-email: diegosaraiva@gmail.com
License: UNKNOWN
Project-URL: Source, https://github.com/jdiego/python-libfprint
Platform: UNKNOWN
